{"cameraMode":{"drawMode":0,"name":"Shaded","section":"Shading Mode"},"sceneLighting":false,"audioPlay":false,"sceneViewState":{"showFog":true,"showMaterialUpdate":false,"showSkybox":false,"showFlares":true,"showImageEffects":true,"showParticleSystems":true},"in2DMode":false,"pivot":{"x":-5.960464477539063e-8,"y":0.0,"z":0.002686113119125366},"rotation":{"x":-0.28921225666999819,"y":-0.3953000009059906,"z":0.1326807737350464,"w":-0.8617374897003174},"size":1.417688012123108,"orthographic":false}